loguru_safe/__init__.py
loguru_safe/__init__.pyi
loguru_safe/_asyncio_loop.py
loguru_safe/_better_exceptions.py
loguru_safe/_colorama.py
loguru_safe/_colorizer.py
loguru_safe/_contextvars.py
loguru_safe/_ctime_functions.py
loguru_safe/_datetime.py
loguru_safe/_defaults.py
loguru_safe/_error_interceptor.py
loguru_safe/_file_sink.py
loguru_safe/_filters.py
loguru_safe/_get_frame.py
loguru_safe/_handler.py
loguru_safe/_locks_machinery.py
loguru_safe/_logger.py
loguru_safe/_recattrs.py
loguru_safe/_simple_sinks.py
loguru_safe/_string_parsers.py
loguru_safe/py.typed
loguru_safe-0.6.0.dist-info/LICENSE
loguru_safe-0.6.0.dist-info/METADATA
loguru_safe-0.6.0.dist-info/WHEEL
loguru_safe-0.6.0.dist-info/top_level.txt
loguru_safe-0.6.0.dist-info/RECORD
